imageai/__init__.py
imageai/api.py
imageai/cli/__init__.py
imageai/cli/analyze.py
imageai/cli/app.py
imageai/cli/detect.py
imageai/cli/noise_law.py
imageai/core/__init__.py
imageai/core/decision.py
imageai/core/evidence.py
imageai/core/io.py
imageai/core/patches.py
imageai/forensics/__init__.py
imageai/forensics/cfa.py
imageai/forensics/jpeg_header.py
imageai/forensics/noise_law.py
imageai/forensics/resampling.py
imageai/forensics/screenshot.py
imageai/forensics/spectral.py
nilparadox_imageai-0.1.0.dist-info/METADATA
nilparadox_imageai-0.1.0.dist-info/WHEEL
nilparadox_imageai-0.1.0.dist-info/entry_points.txt
nilparadox_imageai-0.1.0.dist-info/top_level.txt
nilparadox_imageai-0.1.0.dist-info/RECORD
