Metadata-Version: 2.4
Name: nilparadox-imageai
Version: 0.1.0
Summary: Explainable, physics-based image forensics (AI enhancement, screenshots, resampling) with structured decisions.
Author: Nilanjan Panda
License: MIT
Requires-Python: >=3.9
Requires-Dist: numpy>=1.23
Requires-Dist: pillow>=10.0
Requires-Dist: typer>=0.9
Requires-Dist: rich>=13.0
Requires-Dist: scipy>=1.9
Requires-Dist: pillow-heif>=0.16.0
